ariary/__init__.py
ariary/api_client.py
ariary/client.py
ariary/types.py
ariary/services/__init__.py
ariary/services/payment.py
ariary/services/sms.py
ariary/services/transfer.py
ariary_python_sdk-1.0.1.dist-info/METADATA
ariary_python_sdk-1.0.1.dist-info/WHEEL
ariary_python_sdk-1.0.1.dist-info/top_level.txt
ariary_python_sdk-1.0.1.dist-info/RECORD
