Metadata-Version: 2.4
Name: ariary-python-sdk
Version: 1.0.1
Summary: SDK officiel Python pour l'API de paiement Ariary
Author: Ariary
License: ISC
Keywords: ariary,payment,sms,transfer,api
Classifier: Programming Language :: Python :: 3
Classifier: Programming Language :: Python :: 3.7
Classifier: Programming Language :: Python :: 3.8
Classifier: Programming Language :: Python :: 3.9
Classifier: Programming Language :: Python :: 3.10
Classifier: Programming Language :: Python :: 3.11
Classifier: License :: OSI Approved :: ISC License (ISCL)
Requires-Python: >=3.7
Requires-Dist: requests>=2.28.0
Dynamic: author
Dynamic: classifier
Dynamic: keywords
Dynamic: license
Dynamic: requires-dist
Dynamic: requires-python
Dynamic: summary
